bitcrypt/__init__.py
bitcrypt/core.py
tests/__init__.py
tests/test_HMAC.py
ideal6-1.0.3.dist-info/METADATA
ideal6-1.0.3.dist-info/WHEEL
ideal6-1.0.3.dist-info/top_level.txt
ideal6-1.0.3.dist-info/RECORD
