Metadata-Version: 2.4
Name: ideal6
Version: 1.0.3
Summary: Multi-layer AES encryption library with HMAC integrity verification
Author: AlJoharah
Author-email: cs.alqahtani@gmail.com
Classifier: Programming Language :: Python :: 3
Classifier: License :: OSI Approved :: MIT License
Classifier: Operating System :: OS Independent
Classifier: Topic :: Security :: Cryptography
Classifier: Development Status :: 4 - Beta
Classifier: Intended Audience :: Developers
Requires-Python: >=3.6
Requires-Dist: pycryptodome
Dynamic: author
Dynamic: author-email
Dynamic: classifier
Dynamic: description
Dynamic: requires-dist
Dynamic: requires-python
Dynamic: summary
